{
  "Angels": 66.8,
  "Astros": 84.5,
  "Athletics": 0.6,
  "Blue Jays": 95.1,
  "Braves": 74.0,
  "Brewers": 87.1,
  "Cardinals": 42.0,
  "Cubs": 3.0,
  "Diamondbacks": 0.7,
  "Dodgers": 94.3,
  "Giants": 64.1,
  "Guardians": 16.1,
  "Mariners": 30.8,
  "Marlins": 28.0,
  "Mets": 84.3,
  "Nationals": 0.1,
  "Orioles": 0.0,
  "Padres": 79.8,
  "Phillies": 40.8,
  "Pirates": 0.2,
  "Rangers": 1.6,
  "Rays": 51.6,
  "Red Sox": 37.0,
  "Reds": 0.2,
  "Rockies": 1.5,
  "Royals": 2.6,
  "Tigers": 4.9,
  "Twins": 61.5,
  "White Sox": 51.1,
  "Yankees": 95.8
}